jupyterlab_language_pack_lt_LT/__init__.py
jupyterlab_language_pack_lt_LT/locale/lt_LT/LC_MESSAGES/.gitkeep
jupyterlab_language_pack_lt_LT/locale/lt_LT/LC_MESSAGES/dask_labextension.json
jupyterlab_language_pack_lt_LT/locale/lt_LT/LC_MESSAGES/dask_labextension.mo
jupyterlab_language_pack_lt_LT/locale/lt_LT/LC_MESSAGES/jupyter_archive.json
jupyterlab_language_pack_lt_LT/locale/lt_LT/LC_MESSAGES/jupyter_archive.mo
jupyterlab_language_pack_lt_LT/locale/lt_LT/LC_MESSAGES/jupyter_collaboration.json
jupyterlab_language_pack_lt_LT/locale/lt_LT/LC_MESSAGES/jupyter_collaboration.mo
jupyterlab_language_pack_lt_LT/locale/lt_LT/LC_MESSAGES/jupyter_resource_usage.json
jupyterlab_language_pack_lt_LT/locale/lt_LT/LC_MESSAGES/jupyter_resource_usage.mo
jupyterlab_language_pack_lt_LT/locale/lt_LT/LC_MESSAGES/jupyterlab.json
jupyterlab_language_pack_lt_LT/locale/lt_LT/LC_MESSAGES/jupyterlab.mo
jupyterlab_language_pack_lt_LT/locale/lt_LT/LC_MESSAGES/jupyterlab_git.json
jupyterlab_language_pack_lt_LT/locale/lt_LT/LC_MESSAGES/jupyterlab_git.mo
jupyterlab_language_pack_lt_LT/locale/lt_LT/LC_MESSAGES/jupyterlab_lsp.json
jupyterlab_language_pack_lt_LT/locale/lt_LT/LC_MESSAGES/jupyterlab_lsp.mo
jupyterlab_language_pack_lt_LT/locale/lt_LT/LC_MESSAGES/jupyterlab_recents.json
jupyterlab_language_pack_lt_LT/locale/lt_LT/LC_MESSAGES/jupyterlab_recents.mo
jupyterlab_language_pack_lt_LT/locale/lt_LT/LC_MESSAGES/jupyterlab_search_replace.json
jupyterlab_language_pack_lt_LT/locale/lt_LT/LC_MESSAGES/jupyterlab_search_replace.mo
jupyterlab_language_pack_lt_LT/locale/lt_LT/LC_MESSAGES/jupyterlab_spreadsheet_editor.json
jupyterlab_language_pack_lt_LT/locale/lt_LT/LC_MESSAGES/jupyterlab_spreadsheet_editor.mo
jupyterlab_language_pack_lt_LT/locale/lt_LT/LC_MESSAGES/jupyterlab_tour.json
jupyterlab_language_pack_lt_LT/locale/lt_LT/LC_MESSAGES/jupyterlab_tour.mo
jupyterlab_language_pack_lt_LT/locale/lt_LT/LC_MESSAGES/jupyterlab_widgets.json
jupyterlab_language_pack_lt_lt-4.5.post1.dist-info/METADATA
jupyterlab_language_pack_lt_lt-4.5.post1.dist-info/WHEEL
jupyterlab_language_pack_lt_lt-4.5.post1.dist-info/entry_points.txt
jupyterlab_language_pack_lt_lt-4.5.post1.dist-info/licenses/LICENSE.txt
jupyterlab_language_pack_lt_lt-4.5.post1.dist-info/RECORD
